mozprofile/__init__.py
mozprofile/addons.py
mozprofile/cli.py
mozprofile/diff.py
mozprofile/permissions.py
mozprofile/prefs.py
mozprofile/profile.py
mozprofile/view.py
mozprofile-2.6.1.dist-info/METADATA
mozprofile-2.6.1.dist-info/WHEEL
mozprofile-2.6.1.dist-info/entry_points.txt
mozprofile-2.6.1.dist-info/top_level.txt
mozprofile-2.6.1.dist-info/RECORD
